{
    "001.jpg": [
        "Embroidery Arabesque Design"
    ],
    "002.png": [
        "Futuristic Neon Lights"
    ],
    "003.jpg": [
        "Flower Ornaments"
    ],
    "004.jpg": [
        "Bird design"
    ],
    "005.jpg": [
        "Futuristic Neon Lights"
    ],
    "006.jpg": [
        "Flower Ornaments"
    ],
    "007.jpg": [
        "Kaleidoscopic Patterns"
    ],
    "008.jpg": [
        "Flower Ornaments"
    ],
    "009.jpg": [
        "Flower Ornaments"
    ],
    "010.jpg": [
        "Kaleidoscopic Patterns"
    ],
    "011.jpg": [
        "Flower Ornaments"
    ],
    "012.jpg": [
        "Kaleidoscopic Patterns"
    ],
    "013.jpg": [
        "Paisley"
    ],
    "014.jpg": [
        "Futuristic Neon Lights"
    ],
    "015.jpg": [
        "Feather"
    ],
    "016.jpg": [
        "Flower Ornaments"
    ],
    "017.jpg": [
        "Flower Ornaments"
    ],
    "018.jpg": [
        "Embroidery Arabesque Design"
    ],
    "019.jpg": [],
    "020.jpg": [
        "Embroidery Arabesque Design"
    ],
    "021.jpg": [
        "Tints and shades"
    ],
    "022.jpg": [],
    "023.jpg": [
        "Tints and shades"
    ],
    "024.jpg": [
        "Stained Glass"
    ],
    "025.jpg": [
        "Stained Glass"
    ],
    "026.jpg": [
        "Stained Glass"
    ],
    "027.jpg": [
        "Stained Glass"
    ],
    "028.jpg": [
        "Vertical Symmetry Design"
    ],
    "029.jpg": [
        "Vertical Symmetry Design"
    ],
    "030.jpg": [
        "Vertical Symmetry Design"
    ],
    "031.jpg": [
        "Stained Glass"
    ],
    "032.jpg": [
        "Rectangular Rug"
    ],
    "033.jpg": [
        "Stained Glass"
    ],
    "034.jpg": [
        "Rectangular Rug"
    ],
    "035.jpg": [
        "Rectangular Rug"
    ],
    "036.jpg": [
        "Rectangular Rug"
    ],
    "037.jpg": [
        "Metropolis Pattern"
    ],
    "038.jpg": [
        "Vertical Symmetry Design"
    ],
    "039.jpg": [
        "Feather"
    ],
    "040.jpg": [
        "Stained Glass"
    ],
    "041.jpg": [
        "Futuristic Neon Lights"
    ],
    "042.jpg": [
        "Futuristic Neon Lights"
    ],
    "043.jpg": [
        "Rectangular Rug"
    ],
    "044.jpg": [
        "Futuristic Neon Lights"
    ],
    "045.jpg": [
        "Stained Glass"
    ],
    "046.jpg": [
        "Futuristic Neon Lights"
    ],
    "047.jpg": [
        "Cheetah Pattern"
    ],
    "048.jpg": [
        "Futuristic Neon Lights"
    ],
    "049.jpg": [
        "Futuristic Neon Lights"
    ],
    "050.jpg": [
        "Cheetah Pattern"
    ],
    "051.jpg": [
        "Cheetah Pattern"
    ],
    "052.jpg": [
        "Dots"
    ],
    "053.jpg": [
        "Cheetah Pattern"
    ],
    "054.jpg": [
        "Futuristic Neon Lights"
    ],
    "055.jpg": [
        "Futuristic Neon Lights"
    ],
    "056.jpg": [
        "Dots"
    ],
    "057.jpg": [
        "Dots"
    ],
    "058.jpg": [
        "Cheetah Pattern"
    ],
    "059.jpg": [
        "Woven Design"
    ],
    "060.jpg": [
        "Woven Design"
    ],
    "061.jpg": [
        "Embroidery Arabesque Design"
    ],
    "062.jpg": [
        "Cheetah Pattern"
    ],
    "063.jpg": [
        "Embroidery Arabesque Design"
    ],
    "064.jpg": [
        "Cheetah Pattern"
    ],
    "065.jpg": [
        "Embroidery Arabesque Design"
    ],
    "066.jpg": [
        "Cheetah Pattern"
    ],
    "067.jpg": [
        "Embroidery Arabesque Design"
    ],
    "068.jpg": [
        "Embroidery Arabesque Design"
    ],
    "069.jpg": [
        "Cheetah Pattern"
    ],
    "070.jpg": [
        "Tints and shades"
    ],
    "071.jpg": [
        "Cheetah Pattern"
    ],
    "072.jpg": [
        "Cheetah Pattern"
    ],
    "073.jpg": [
        "Cheetah Pattern"
    ],
    "074.jpg": [
        "Stained Glass"
    ],
    "075.jpg": [
        "Cheetah Pattern"
    ],
    "076.jpg": [
        "Tiles"
    ],
    "077.jpg": [
        "Bird design"
    ],
    "078.jpg": [
        "Dots"
    ],
    "079.jpg": [
        "Flower Ornaments"
    ],
    "080.jpg": [
        "Bird design"
    ],
    "081.jpg": [
        "Tints and shades"
    ],
    "082.jpg": [
        "Rainforest"
    ],
    "083.jpg": [
        "Rainforest"
    ],
    "084.jpg": [
        "Tints and shades"
    ],
    "085.jpg": [
        "Rainforest"
    ],
    "086.jpg": [
        "Tiles"
    ],
    "087.jpg": [
        "Colorfull Grid"
    ],
    "088.jpg": [
        "Stained Glass"
    ],
    "089.jpg": [
        "Colorfull Grid"
    ],
    "090.jpg": [
        "Colorfull Grid"
    ],
    "091.jpg": [
        "Flower Grid"
    ],
    "092.jpg": [
        "Flower Grid"
    ],
    "093.jpg": [
        "Flower Grid"
    ],
    "094.jpg": [
        "Flower Grid"
    ],
    "095.jpg": [
        "Flower Grid"
    ],
    "096.jpg": [
        "Woven Design"
    ],
    "097.jpg": [
        "Woven Design"
    ],
    "098.jpg": [
        "Woven Design"
    ],
    "099.jpg": [
        "Kaleidoscopic Patterns"
    ],
    "100.jpg": [
        "Tiles"
    ],
    "101.jpg": [
        "Tints and shades"
    ],
    "102.jpg": [
        "Kaleidoscopic Patterns"
    ],
    "103.jpg": [
        "Tiles"
    ],
    "104.jpg": [
        "Stained Glass"
    ],
    "105.jpg": [
        "Kaleidoscopic Patterns"
    ],
    "106.jpg": [
        "Flower Ornaments"
    ],
    "107.jpg": [
        "Paisley"
    ],
    "108.jpg": [
        "Woven Design"
    ],
    "109.jpg": [
        "Woven Design"
    ],
    "110.jpg": [
        "Woven Design"
    ],
    "111.jpg": [
        "Embroidery Arabesque Design"
    ],
    "112.jpg": [
        "Kaleidoscopic Patterns"
    ],
    "113.jpg": [
        "Embroidery Arabesque Design"
    ],
    "114.jpg": [
        "Embroidery Arabesque Design"
    ],
    "115.jpg": [
        "Circle Pattern"
    ],
    "116.jpg": [
        "Circle Pattern"
    ],
    "117.jpg": [
        "Quilt Design"
    ],
    "118.jpg": [
        "Quilt Design"
    ]
}